Metadata-Version: 2.4
Name: tmp-test-vllm-tpu
Version: 0.0.1
Summary: A high-throughput and memory-efficient inference and serving engine for LLMs
Author: vLLM Team
License-Expression: Apache-2.0
Project-URL: Homepage, https://github.com/vllm-project/vllm
Project-URL: Documentation, https://docs.vllm.ai/en/latest/
Project-URL: Slack, https://slack.vllm.ai/
Classifier: Programming Language :: Python :: 3.9
Classifier: Programming Language :: Python :: 3.10
Classifier: Programming Language :: Python :: 3.11
Classifier: Programming Language :: Python :: 3.12
Classifier: Intended Audience :: Developers
Classifier: Intended Audience :: Information Technology
Classifier: Intended Audience :: Science/Research
Classifier: Topic :: Scientific/Engineering :: Artificial Intelligence
Classifier: Topic :: Scientific/Engineering :: Information Analysis
Requires-Python: <3.13,>=3.9
License-File: LICENSE
Requires-Dist: regex
Requires-Dist: cachetools
Requires-Dist: psutil
Requires-Dist: sentencepiece
Requires-Dist: numpy
Requires-Dist: requests>=2.26.0
Requires-Dist: tqdm
Requires-Dist: blake3
Requires-Dist: py-cpuinfo
Requires-Dist: transformers>=4.55.0
Requires-Dist: tokenizers>=0.21.1
Requires-Dist: protobuf
Requires-Dist: fastapi[standard]>=0.115.0
Requires-Dist: aiohttp
Requires-Dist: openai>=1.99.1
Requires-Dist: pydantic>=2.10
Requires-Dist: prometheus_client>=0.18.0
Requires-Dist: pillow
Requires-Dist: prometheus-fastapi-instrumentator>=7.0.0
Requires-Dist: tiktoken>=0.6.0
Requires-Dist: lm-format-enforcer<0.11,>=0.10.11
Requires-Dist: llguidance<0.8.0,>=0.7.11; platform_machine == "x86_64" or platform_machine == "arm64" or platform_machine == "aarch64"
Requires-Dist: outlines_core==0.2.10
Requires-Dist: diskcache==5.6.3
Requires-Dist: lark==1.2.2
Requires-Dist: xgrammar==0.1.21; platform_machine == "x86_64" or platform_machine == "aarch64" or platform_machine == "arm64"
Requires-Dist: typing_extensions>=4.10
Requires-Dist: filelock>=3.16.1
Requires-Dist: partial-json-parser
Requires-Dist: pyzmq>=25.0.0
Requires-Dist: msgspec
Requires-Dist: gguf>=0.13.0
Requires-Dist: importlib_metadata; python_version < "3.10"
Requires-Dist: mistral_common[audio,image]>=1.8.2
Requires-Dist: opencv-python-headless>=4.11.0
Requires-Dist: pyyaml
Requires-Dist: six>=1.16.0; python_version > "3.11"
Requires-Dist: setuptools<80,>=77.0.3; python_version > "3.11"
Requires-Dist: einops
Requires-Dist: compressed-tensors==0.10.2
Requires-Dist: depyf==0.19.0
Requires-Dist: cloudpickle
Requires-Dist: watchfiles
Requires-Dist: python-json-logger
Requires-Dist: scipy
Requires-Dist: ninja
Requires-Dist: pybase64
Requires-Dist: cbor2
Requires-Dist: setproctitle
Requires-Dist: openai-harmony>=0.0.3
Requires-Dist: cmake>=3.26.1
Requires-Dist: packaging>=24.2
Requires-Dist: setuptools-scm>=8
Requires-Dist: wheel
Requires-Dist: jinja2>=3.1.6
Requires-Dist: ray[default]
Requires-Dist: ray[data]
Requires-Dist: setuptools==78.1.0
Requires-Dist: nixl==0.3.0
Requires-Dist: tpu_info==0.4.0
Requires-Dist: torch_xla[pallas,tpu]==2.8.0
Provides-Extra: bench
Requires-Dist: pandas; extra == "bench"
Requires-Dist: datasets; extra == "bench"
Provides-Extra: tensorizer
Requires-Dist: tensorizer==2.10.1; extra == "tensorizer"
Provides-Extra: fastsafetensors
Requires-Dist: fastsafetensors>=0.1.10; extra == "fastsafetensors"
Provides-Extra: runai
Requires-Dist: runai-model-streamer>=0.13.3; extra == "runai"
Requires-Dist: runai-model-streamer-s3; extra == "runai"
Requires-Dist: boto3; extra == "runai"
Provides-Extra: audio
Requires-Dist: librosa; extra == "audio"
Requires-Dist: soundfile; extra == "audio"
Requires-Dist: mistral_common[audio]; extra == "audio"
Provides-Extra: video
Provides-Extra: flashinfer
Requires-Dist: flashinfer-python==0.2.11; extra == "flashinfer"
Dynamic: license-file
Dynamic: provides-extra
Dynamic: requires-dist
